wpm/__init__.py
wpm/__main__.py
wpm/commandline.py
wpm/config.py
wpm/convert.py
wpm/devfeature.py
wpm/difficulty.py
wpm/error.py
wpm/game.py
wpm/gauss.py
wpm/histogram.py
wpm/quotes.py
wpm/record.py
wpm/screen.py
wpm/stats.py
wpm/data/examples.json.gz
wpm-1.51.5.data/scripts/wpm
wpm-1.51.5.dist-info/LICENSE.txt
wpm-1.51.5.dist-info/METADATA
wpm-1.51.5.dist-info/WHEEL
wpm-1.51.5.dist-info/top_level.txt
wpm-1.51.5.dist-info/zip-safe
wpm-1.51.5.dist-info/RECORD
