Metadata-Version: 2.1
Name: wpm
Version: 1.51.5
Summary: Console app for measuring typing speed in words per minute (WPM)
Home-page: https://github.com/cslarsen/wpm
Author: Christian Stigen Larsen
Author-email: csl@csl.name
License: https://www.gnu.org/licenses/agpl-3.0.html
Download-URL: https://github.com/cslarsen/wpm/tarball/v1.51.5
Keywords: wpm,typing,typist
Platform: unix
Platform: linux
Platform: osx
Platform: cygwin
Classifier: Development Status :: 3 - Alpha
Classifier: Environment :: Console
Classifier: Natural Language :: English
Classifier: Operating System :: MacOS :: MacOS X
Classifier: Operating System :: Microsoft :: Windows
Classifier: Operating System :: POSIX
Classifier: Operating System :: Unix
Classifier: Programming Language :: Python
Classifier: Programming Language :: Python :: 2
Classifier: Programming Language :: Python :: 2.6
Classifier: Programming Language :: Python :: 2.7
Classifier: Programming Language :: Python :: 3
Classifier: Programming Language :: Python :: 3.1
Classifier: Programming Language :: Python :: 3.2
Classifier: Programming Language :: Python :: 3.3
Classifier: Programming Language :: Python :: 3.4
Classifier: Programming Language :: Python :: 3.5
Classifier: Programming Language :: Python :: 3.6
Classifier: Programming Language :: Python :: 3.7
Classifier: Programming Language :: Python :: Implementation :: PyPy
Requires-Dist: setuptools
